odbctools/__init__.py
odbctools/odbcmanager/__init__.py
odbctools/odbcmanager/odbcmanager.py
odbctools/odbcmanager/pypyodbc.py
odbctools/tests/__init__.py
odbctools/tests/odbcmanager_tests.py
odbctools-0.7.1.dist-info/licenses/LICENSE
odbctools-0.7.1.dist-info/METADATA
odbctools-0.7.1.dist-info/WHEEL
odbctools-0.7.1.dist-info/top_level.txt
odbctools-0.7.1.dist-info/RECORD
