Metadata-Version: 2.4
Name: odbctools
Version: 0.7.1
Summary: A set of tools to simplify connecting to and working with an ODBC data source
Home-page: https://github.com/N-C-C/odbctools
Author: Andrew Yatsko
Author-email: Andrew Yatsko <ayatsko@live.com>
Maintainer-email: Will Fulmer <fulmerwil@gmail.com>, John Glasgow <john@johnglasgow.dev>
License-Expression: MIT
Project-URL: Homepage, https://github.com/N-C-C/odbctools
Project-URL: Repository, https://github.com/N-C-C/odbctools.git
Keywords: odbc,database,data,sql,informix
Classifier: Development Status :: 4 - Beta
Classifier: Topic :: Database
Classifier: Environment :: Console
Classifier: Intended Audience :: Developers
Classifier: Programming Language :: Python
Requires-Python: >=3.12
License-File: LICENSE
Requires-Dist: setuptools>=35.0.0
Requires-Dist: pypyodbc>=1.3.6
Requires-Dist: uv>=0.7.13
Dynamic: author
Dynamic: home-page
Dynamic: license-file
